odoo/addons/fleet_vehicle_service_kanban/README.rst
odoo/addons/fleet_vehicle_service_kanban/__init__.py
odoo/addons/fleet_vehicle_service_kanban/__manifest__.py
odoo/addons/fleet_vehicle_service_kanban/data/fleet_vehicle_log_services_stage_data.xml
odoo/addons/fleet_vehicle_service_kanban/data/mail_message_subtype_data.xml
odoo/addons/fleet_vehicle_service_kanban/i18n/fleet_vehicle_service_kanban.pot
odoo/addons/fleet_vehicle_service_kanban/i18n/it.po
odoo/addons/fleet_vehicle_service_kanban/i18n/pt_BR.po
odoo/addons/fleet_vehicle_service_kanban/models/__init__.py
odoo/addons/fleet_vehicle_service_kanban/models/fleet_vehicle_log_services.py
odoo/addons/fleet_vehicle_service_kanban/models/fleet_vehicle_log_services_stage.py
odoo/addons/fleet_vehicle_service_kanban/models/fleet_vehicle_log_services_tag.py
odoo/addons/fleet_vehicle_service_kanban/readme/CONTRIBUTORS.rst
odoo/addons/fleet_vehicle_service_kanban/readme/DESCRIPTION.rst
odoo/addons/fleet_vehicle_service_kanban/security/ir.model.access.csv
odoo/addons/fleet_vehicle_service_kanban/static/description/icon.png
odoo/addons/fleet_vehicle_service_kanban/static/description/index.html
odoo/addons/fleet_vehicle_service_kanban/tests/__init__.py
odoo/addons/fleet_vehicle_service_kanban/tests/common.py
odoo/addons/fleet_vehicle_service_kanban/tests/test_vehicle_log_services.py
odoo/addons/fleet_vehicle_service_kanban/views/fleet_service_type_views.xml
odoo/addons/fleet_vehicle_service_kanban/views/fleet_vehicle_log_services_stage_views.xml
odoo/addons/fleet_vehicle_service_kanban/views/fleet_vehicle_log_services_tag_views.xml
odoo/addons/fleet_vehicle_service_kanban/views/fleet_vehicle_log_services_views.xml
odoo/addons/fleet_vehicle_service_kanban/views/mail_activity_type_views.xml
odoo14_addon_fleet_vehicle_service_kanban-14.0.1.0.1.dist-info/METADATA
odoo14_addon_fleet_vehicle_service_kanban-14.0.1.0.1.dist-info/WHEEL
odoo14_addon_fleet_vehicle_service_kanban-14.0.1.0.1.dist-info/top_level.txt
odoo14_addon_fleet_vehicle_service_kanban-14.0.1.0.1.dist-info/RECORD
